{"cameraMode":{"drawMode":0,"name":"Shaded","section":"Shading Mode"},"sceneLighting":true,"audioPlay":false,"sceneViewState":{"showFog":true,"showMaterialUpdate":false,"showSkybox":true,"showFlares":true,"showImageEffects":true,"showParticleSystems":true},"in2DMode":false,"pivot":{"x":985.5132446289063,"y":175.2093048095703,"z":-11.57489013671875},"rotation":{"x":-0.0003118634922429919,"y":-0.006902923807501793,"z":0.00000224345467358944,"w":-0.9999761581420898},"size":279.1575012207031,"orthographic":false}